{"cameraMode":{"drawMode":0,"name":"Shaded","section":"Shading Mode"},"sceneLighting":true,"audioPlay":false,"sceneViewState":{"showFog":true,"showMaterialUpdate":false,"showSkybox":true,"showFlares":true,"showImageEffects":true,"showParticleSystems":true},"in2DMode":false,"pivot":{"x":26.1953125,"y":-6.557703018188477,"z":-7.571157455444336},"rotation":{"x":0.24095620214939118,"y":-0.42293980717658999,"z":0.11774297803640366,"w":0.8655934929847717},"size":24.32330894470215,"orthographic":false}